finvizlite/__init__.py
finvizlite-0.1.2.dist-info/LICENSE
finvizlite-0.1.2.dist-info/METADATA
finvizlite-0.1.2.dist-info/WHEEL
finvizlite-0.1.2.dist-info/top_level.txt
finvizlite-0.1.2.dist-info/RECORD
