Metadata-Version: 2.1
Name: finvizlite
Version: 0.1.2
Summary: A lightweight finviz screener scraper
Home-page: https://github.com/andr3w321/finvizlite
Author: Andrew Rennhack
Author-email: andr3w321@gmail.com
License: MIT
License-File: LICENSE
Requires-Dist: requests
Requires-Dist: bs4
Requires-Dist: lxml
Requires-Dist: pandas
